flaskeleton_cli/__init__.py
flaskeleton_cli/__main__.py
flaskeleton_cli/consts.py
flaskeleton_cli/core.py
flaskeleton_cli-0.1.4.dist-info/LICENSE
flaskeleton_cli-0.1.4.dist-info/METADATA
flaskeleton_cli-0.1.4.dist-info/WHEEL
flaskeleton_cli-0.1.4.dist-info/entry_points.txt
flaskeleton_cli-0.1.4.dist-info/RECORD
