Metadata-Version: 2.1
Name: flaskeleton-cli
Version: 0.1.4
Summary: CLI to create a Flask-based project
License: MIT
Author: William B M Sampaio
Author-email: 56176702+WilliamSampaio@users.noreply.github.com
Requires-Python: >=3.11,<4.0
Classifier: License :: OSI Approved :: MIT License
Classifier: Programming Language :: Python :: 3
Classifier: Programming Language :: Python :: 3.11
Classifier: Programming Language :: Python :: 3.12
Requires-Dist: rich (>=13.7.0,<14.0.0)
Requires-Dist: typer[all] (>=0.9.0,<0.10.0)
